<?xml version="1.0" encoding="utf-8"?>
<TextureAtlas imagePath="PicoPlays.png">
	<!-- Created with Adobe Animate version 22.0.5.191 -->
	<!-- http://www.adobe.com/products/animate.html -->
	<SubTexture name="Down pose0000" x="0" y="0" width="699" height="401"/>
	<SubTexture name="Down pose0001" x="0" y="0" width="699" height="401"/>
	<SubTexture name="Down pose0002" x="699" y="0" width="699" height="401"/>
	<SubTexture name="Down pose0003" x="699" y="0" width="699" height="401"/>
	<SubTexture name="Down pose0004" x="1398" y="0" width="699" height="401"/>
	<SubTexture name="Down pose0005" x="1398" y="0" width="699" height="401"/>
	<SubTexture name="Down pose0006" x="2097" y="0" width="699" height="401"/>
	<SubTexture name="Down pose0007" x="2097" y="0" width="699" height="401"/>
	<SubTexture name="Down pose0008" x="2796" y="0" width="699" height="401"/>
	<SubTexture name="Down pose0009" x="2796" y="0" width="699" height="401"/>
	<SubTexture name="Down pose0010" x="3495" y="0" width="699" height="401"/>
	<SubTexture name="Down pose0011" x="3495" y="0" width="699" height="401"/>
	<SubTexture name="IDLE0000" x="4194" y="0" width="581" height="583"/>
	<SubTexture name="IDLE0001" x="4194" y="0" width="581" height="583"/>
	<SubTexture name="IDLE0002" x="4775" y="0" width="581" height="583"/>
	<SubTexture name="IDLE0003" x="4775" y="0" width="581" height="583"/>
	<SubTexture name="IDLE0004" x="5356" y="0" width="581" height="583"/>
	<SubTexture name="IDLE0005" x="5356" y="0" width="581" height="583"/>
	<SubTexture name="IDLE0006" x="5937" y="0" width="581" height="583"/>
	<SubTexture name="IDLE0007" x="5937" y="0" width="581" height="583"/>
	<SubTexture name="IDLE0008" x="6518" y="0" width="581" height="583"/>
	<SubTexture name="IDLE0009" x="6518" y="0" width="581" height="583"/>
	<SubTexture name="IDLE0010" x="7099" y="0" width="581" height="583"/>
	<SubTexture name="IDLE0011" x="7099" y="0" width="581" height="583"/>
	<SubTexture name="IDLE0012" x="0" y="583" width="581" height="583"/>
	<SubTexture name="IDLE0013" x="0" y="583" width="581" height="583"/>
	<SubTexture name="LEFT POSE0000" x="581" y="583" width="795" height="498"/>
	<SubTexture name="LEFT POSE0001" x="581" y="583" width="795" height="498"/>
	<SubTexture name="LEFT POSE0002" x="1376" y="583" width="795" height="498"/>
	<SubTexture name="LEFT POSE0003" x="2171" y="583" width="795" height="498"/>
	<SubTexture name="LEFT POSE0004" x="2966" y="583" width="795" height="498"/>
	<SubTexture name="LEFT POSE0005" x="2966" y="583" width="795" height="498"/>
	<SubTexture name="LEFT POSE0006" x="3761" y="583" width="795" height="498"/>
	<SubTexture name="LEFT POSE0007" x="3761" y="583" width="795" height="498"/>
	<SubTexture name="LEFT POSE0008" x="4556" y="583" width="795" height="498"/>
	<SubTexture name="LEFT POSE0009" x="4556" y="583" width="795" height="498"/>
	<SubTexture name="LEFT POSE0010" x="5351" y="583" width="795" height="498"/>
	<SubTexture name="LEFT POSE0011" x="5351" y="583" width="795" height="498"/>
	<SubTexture name="MISS DOWN0000" x="6146" y="583" width="705" height="428"/>
	<SubTexture name="MISS DOWN0001" x="6851" y="583" width="705" height="428"/>
	<SubTexture name="MISS DOWN0002" x="0" y="1166" width="705" height="428"/>
	<SubTexture name="MISS DOWN0003" x="705" y="1166" width="705" height="428"/>
	<SubTexture name="MISS DOWN0004" x="1410" y="1166" width="705" height="428"/>
	<SubTexture name="MISS DOWN0005" x="0" y="1166" width="705" height="428"/>
	<SubTexture name="MISS DOWN0006" x="705" y="1166" width="705" height="428"/>
	<SubTexture name="MISS DOWN0007" x="1410" y="1166" width="705" height="428"/>
	<SubTexture name="MISS LEFT0000" x="2115" y="1166" width="787" height="526"/>
	<SubTexture name="MISS LEFT0001" x="2902" y="1166" width="787" height="526"/>
	<SubTexture name="MISS LEFT0002" x="3689" y="1166" width="787" height="526"/>
	<SubTexture name="MISS LEFT0003" x="4476" y="1166" width="787" height="526"/>
	<SubTexture name="MISS LEFT0004" x="5263" y="1166" width="787" height="526"/>
	<SubTexture name="MISS LEFT0005" x="3689" y="1166" width="787" height="526"/>
	<SubTexture name="MISS LEFT0006" x="4476" y="1166" width="787" height="526"/>
	<SubTexture name="MISS LEFT0007" x="5263" y="1166" width="787" height="526"/>
	<SubTexture name="MISS RIGHT0000" x="6050" y="1166" width="598" height="568"/>
	<SubTexture name="MISS RIGHT0001" x="6648" y="1166" width="598" height="568"/>
	<SubTexture name="MISS RIGHT0002" x="7246" y="1166" width="598" height="568"/>
	<SubTexture name="MISS RIGHT0003" x="0" y="1734" width="598" height="568"/>
	<SubTexture name="MISS RIGHT0004" x="598" y="1734" width="598" height="568"/>
	<SubTexture name="MISS RIGHT0005" x="7246" y="1166" width="598" height="568"/>
	<SubTexture name="MISS RIGHT0006" x="0" y="1734" width="598" height="568"/>
	<SubTexture name="MISS UP0000" x="1196" y="1734" width="654" height="621"/>
	<SubTexture name="MISS UP0001" x="1850" y="1734" width="654" height="621"/>
	<SubTexture name="MISS UP0002" x="2504" y="1734" width="654" height="621"/>
	<SubTexture name="MISS UP0003" x="3158" y="1734" width="654" height="621"/>
	<SubTexture name="MISS UP0004" x="3812" y="1734" width="654" height="621"/>
	<SubTexture name="MISS UP0005" x="4466" y="1734" width="654" height="621"/>
	<SubTexture name="MISS UP0006" x="3158" y="1734" width="654" height="621"/>
	<SubTexture name="MISS UP0007" x="3812" y="1734" width="654" height="621"/>
	<SubTexture name="RIGHT Pose0000" x="5120" y="1734" width="581" height="573"/>
	<SubTexture name="RIGHT Pose0001" x="5701" y="1734" width="581" height="573"/>
	<SubTexture name="RIGHT Pose0002" x="6282" y="1734" width="581" height="573"/>
	<SubTexture name="RIGHT Pose0003" x="6863" y="1734" width="581" height="573"/>
	<SubTexture name="RIGHT Pose0004" x="7444" y="1734" width="581" height="573"/>
	<SubTexture name="RIGHT Pose0005" x="0" y="2355" width="581" height="573"/>
	<SubTexture name="RIGHT Pose0006" x="581" y="2355" width="581" height="573"/>
	<SubTexture name="RIGHT Pose0007" x="1162" y="2355" width="581" height="573"/>
	<SubTexture name="RIGHT Pose0008" x="1743" y="2355" width="581" height="573"/>
	<SubTexture name="RIGHT Pose0009" x="2324" y="2355" width="581" height="573"/>
	<SubTexture name="UP POSE0000" x="2905" y="2355" width="726" height="668"/>
	<SubTexture name="UP POSE0001" x="3631" y="2355" width="726" height="668"/>
	<SubTexture name="UP POSE0002" x="4357" y="2355" width="726" height="668"/>
	<SubTexture name="UP POSE0003" x="5083" y="2355" width="726" height="668"/>
	<SubTexture name="UP POSE0004" x="5809" y="2355" width="726" height="668"/>
	<SubTexture name="UP POSE0005" x="6535" y="2355" width="726" height="668"/>
	<SubTexture name="UP POSE0006" x="7261" y="2355" width="726" height="668"/>
	<SubTexture name="UP POSE0007" x="0" y="3023" width="726" height="668"/>
	<SubTexture name="UP POSE0008" x="726" y="3023" width="726" height="668"/>
	<SubTexture name="UP POSE0009" x="1452" y="3023" width="726" height="668"/>
	<SubTexture name="UP POSE0010" x="2178" y="3023" width="726" height="668"/>
	<SubTexture name="UP POSE0011" x="2904" y="3023" width="726" height="668"/>
</TextureAtlas>
